inventree_rolling_stocktake-0.1.0.dist-info/licenses/LICENSE
rolling_stocktake/__init__.py
rolling_stocktake/core.py
rolling_stocktake/serializers.py
rolling_stocktake/views.py
rolling_stocktake/static/Dashboard.js
rolling_stocktake/static/Dashboard.js.map
rolling_stocktake/static/.vite/manifest.json
rolling_stocktake/static/assets/messages-69-_sjHD.js
rolling_stocktake/static/assets/messages-69-_sjHD.js.map
rolling_stocktake/static/assets/messages-BEswDnCf.js
rolling_stocktake/static/assets/messages-BEswDnCf.js.map
rolling_stocktake/static/assets/messages-Bbih3APe.js
rolling_stocktake/static/assets/messages-Bbih3APe.js.map
rolling_stocktake/static/assets/messages-BeXXP-7l.js
rolling_stocktake/static/assets/messages-BeXXP-7l.js.map
rolling_stocktake/static/assets/messages-CLyklZqY.js
rolling_stocktake/static/assets/messages-CLyklZqY.js.map
rolling_stocktake/static/assets/messages-D9qwu3wf.js
rolling_stocktake/static/assets/messages-D9qwu3wf.js.map
rolling_stocktake/static/assets/messages-DkHhdO24.js
rolling_stocktake/static/assets/messages-DkHhdO24.js.map
rolling_stocktake/static/assets/messages-_n3iDani.js
rolling_stocktake/static/assets/messages-_n3iDani.js.map
rolling_stocktake/static/assets/messages-ePtIPDKQ.js
rolling_stocktake/static/assets/messages-ePtIPDKQ.js.map
rolling_stocktake/static/assets/messages-tRU--3W1.js
rolling_stocktake/static/assets/messages-tRU--3W1.js.map
inventree_rolling_stocktake-0.1.0.dist-info/METADATA
inventree_rolling_stocktake-0.1.0.dist-info/WHEEL
inventree_rolling_stocktake-0.1.0.dist-info/entry_points.txt
inventree_rolling_stocktake-0.1.0.dist-info/top_level.txt
inventree_rolling_stocktake-0.1.0.dist-info/RECORD
