Metadata-Version: 2.4
Name: inventree-rolling-stocktake
Version: 0.1.0
Summary: Support rolling stocktake for InvenTree
Author-email: Oliver Walters <oliver.henry.walters@gmail.com>
License-Expression: MIT
Project-URL: Homepage, https://github.com/inventree/rolling-stocktake-plugin
Keywords: inventree,plugin
Classifier: Programming Language :: Python :: 3
Classifier: Operating System :: OS Independent
Classifier: Framework :: InvenTree
Requires-Python: >=3.9
License-File: LICENSE
Dynamic: license-file
